{
    "concept_id": "concept_0024a",
    "name": "Concept 0024A - Claim Denied After Member Terminated_updated...",
    "description": "Auditing logic for Claim Denied After Member Terminated_updated",
    "overpayment_conditions": {
        "SBSB_ID": "Must be Same",
        "MEME_SFX": "Must be Same"
    },
    "explanation_templates": {
        "valid": "The claims are valid based on differing key identifiers.",
        "duplicate": "Criteria met for Claim Denied After Member Terminated_updated showing improper duplicate or conflicting billing."
    }
}